{
	"name": "child pipeline",
	"properties": {
		"activities": [
			{
				"name": "Set variable1",
				"type": "SetVariable",
				"dependsOn": [],
				"policy": {
					"secureOutput": false,
					"secureInput": false
				},
				"typeProperties": {
					"variableName": "myvar",
					"value": "hcjh"
				}
			},
			{
				"name": "Set variable2",
				"type": "SetVariable",
				"dependsOn": [
					{
						"activity": "Set variable1",
						"dependencyConditions": [
							"Failed"
						]
					}
				],
				"policy": {
					"secureOutput": false,
					"secureInput": false
				},
				"userProperties": [],
				"typeProperties": {
					"variableName": "myvar",
					"value": 6
				}
			}
		],
		"variables": {
			"myvar": {
				"type": "Integer"
			}
		},
		"annotations": []
	}
}